time_tracker_tui/__about__.py
time_tracker_tui/__init__.py
time_tracker_tui/__main__.py
time_tracker_tui/app.py
time_tracker_tui/createdb.sql
time_tracker_tui/db.py
time_tracker_tui/definition.py
time_tracker_tui/fwidget.py
time_tracker_tui/stopwatch.py
time_tracker_tui/styles.py
time_tracker_tui/views/help_view.py
time_tracker_tui/views/main_view.py
time_tracker_tui/widgets/__init__.py
time_tracker_tui/widgets/info.py
time_tracker_tui/widgets/input_text.py
time_tracker_tui/widgets/time_table.py
time_tracker_tui/widgets/timer.py
time_tracker_tui-0.3.4.dist-info/entry_points.txt
time_tracker_tui-0.3.4.dist-info/LICENSE
time_tracker_tui-0.3.4.dist-info/WHEEL
time_tracker_tui-0.3.4.dist-info/METADATA
time_tracker_tui-0.3.4.dist-info/RECORD
